RMVtransport/__init__.py
RMVtransport/const.py
RMVtransport/errors.py
RMVtransport/rmvjourney.py
RMVtransport/rmvtransport.py
RMVtransport/rmvtravel.py
PyRMVtransport-0.3.2.dist-info/LICENSE
PyRMVtransport-0.3.2.dist-info/WHEEL
PyRMVtransport-0.3.2.dist-info/METADATA
PyRMVtransport-0.3.2.dist-info/RECORD
