Metadata-Version: 2.1
Name: PyRMVtransport
Version: 0.3.2
Summary: Python library to make use of transport information from opendata.rmv.de.
Home-page: https://github.com/cgtobi/PyRMVtransport
License: MIT
Author: cgtobi
Author-email: cgtobi@gmail.com
Requires-Python: >=3.6
Classifier: License :: OSI Approved :: MIT License
Requires-Dist: async-timeout
Requires-Dist: lxml
Requires-Dist: httpx
Requires-Dist: pytest >= 5.2.2 ; extra == "test"
Requires-Dist: pytest-cov >= 2.8.1 ; extra == "test"
Requires-Dist: pytest-asyncio ; extra == "test"
Requires-Dist: pylint ; extra == "test"
Requires-Dist: tox ; extra == "test"
Requires-Dist: pytest-mock ; extra == "test"
Requires-Dist: pytest-httpx ; extra == "test"
Requires-Dist: asynctest ; extra == "test"
Requires-Dist: codecov ; extra == "test"
Requires-Dist: coverage ; extra == "test"
Requires-Dist: mock ; extra == "test"
Requires-Dist: flake8 ; extra == "test"
Requires-Dist: mypy ; extra == "test"
Requires-Dist: bandit ; extra == "test"
Requires-Dist: pre-commit ; extra == "test"
Requires-Dist: black ; extra == "test"
Provides-Extra: test
